ragready/__init__.py
ragready/extractors.py
ragready-0.2.1.dist-info/METADATA
ragready-0.2.1.dist-info/WHEEL
ragready-0.2.1.dist-info/top_level.txt
ragready-0.2.1.dist-info/RECORD
