Metadata-Version: 2.4
Name: ragready
Version: 0.2.1
Summary: Unified data extraction and preprocessing toolkit for Retrieval-Augmented Generation (RAG) pipelines.
Author-email: Kwadwo Daddy Nyame Owusu-Boakye <kwadwo.owusuboakye@outlook.com>
License: MIT
Project-URL: Homepage, https://github.com/knowusuboaky/ragready
Project-URL: Documentation, https://github.com/knowusuboaky/ragready#readme
Project-URL: Source, https://github.com/knowusuboaky/ragready
Project-URL: Issues, https://github.com/knowusuboaky/ragready/issues
Keywords: rag,retrieval,llm,extractor,data,pipeline,metadata,document,ingest,unstructured
Classifier: Programming Language :: Python :: 3
Classifier: License :: OSI Approved :: MIT License
Classifier: Operating System :: OS Independent
Classifier: Intended Audience :: Developers
Classifier: Intended Audience :: Information Technology
Classifier: Topic :: Software Development :: Libraries
Classifier: Topic :: Text Processing :: General
Requires-Python: >=3.9
Requires-Dist: markitdown[all]
Requires-Dist: gitpython
Requires-Dist: atlassian-python-api
Requires-Dist: requests
Requires-Dist: beautifulsoup4
Requires-Dist: lxml
Requires-Dist: tqdm
Requires-Dist: pandas
Requires-Dist: pdfplumber
Requires-Dist: python-docx
Requires-Dist: python-pptx
Requires-Dist: pydub
Provides-Extra: dev
Requires-Dist: pytest; extra == "dev"
Requires-Dist: ruff; extra == "dev"
Requires-Dist: mypy; extra == "dev"
Requires-Dist: pre-commit; extra == "dev"
Requires-Dist: build; extra == "dev"
Requires-Dist: twine; extra == "dev"
Provides-Extra: converters-docx
Requires-Dist: markitdown[docx]>=0.2.1; extra == "converters-docx"
